CHANGELOG.md
MANIFEST.in
README.md
VERSION
graafilohi.py
setup.cfg
setup.py
graafilohi.egg-info/PKG-INFO
graafilohi.egg-info/SOURCES.txt
graafilohi.egg-info/dependency_links.txt
graafilohi.egg-info/requires.txt
graafilohi.egg-info/top_level.txt