Metadata-Version: 2.1
Name: graafilohi
Version: 1.1.3
Summary: Library for defining runnable pipelines as graphs
Home-page: https://gitlab.com/blissfulreboot/python/graafilohi
Author: Aki Mäkinen
Author-email: nenshou.sora@gmail.com
License: MIT
Platform: UNKNOWN
Classifier: Development Status :: 3 - Alpha
Classifier: Intended Audience :: Developers
Classifier: Topic :: Software Development
Classifier: License :: OSI Approved :: MIT License
Classifier: Programming Language :: Python :: 3
Classifier: Programming Language :: Python :: 3.6
